adapter_client/__init__.py
adapter_client/apps.py
adapter_client/config.py
adapter_client/models.py
adapter_client/tasks.py
adapter_client/utils.py
adapter_client/adapters/__init__.py
adapter_client/adapters/base.py
adapter_client/adapters/db.py
adapter_client/adapters/smev/__init__.py
adapter_client/adapters/smev/adapter.py
adapter_client/adapters/smev/interfaces/__init__.py
adapter_client/adapters/smev/interfaces/base.py
adapter_client/adapters/smev/interfaces/s3_storage/__init__.py
adapter_client/adapters/smev/interfaces/s3_storage/interface.py
adapter_client/adapters/smev/interfaces/soap/__init__.py
adapter_client/adapters/smev/interfaces/soap/interface.py
adapter_client/adapters/smev/interfaces/soap/schema/adapter.wsdl
adapter_client/adapters/smev/interfaces/soap/schema/smev-service-adapter-faults.xsd
adapter_client/adapters/smev/interfaces/soap/schema/smev-service-adapter-types.xsd
adapter_client/adapters/smev/logging/__init__.py
adapter_client/adapters/smev/logging/opensearch.py
adapter_client/adapters/smev/services/__init__.py
adapter_client/adapters/smev/services/base.py
adapter_client/adapters/smev/services/registry.py
adapter_client/core/__init__.py
adapter_client/core/services.py
adapter_client/core/domain/__init__.py
adapter_client/core/domain/model.py
adapter_client/migrations/0001_initial.py
adapter_client/migrations/0002_alter_journalentry_options_config_adapter_interface_and_more.py
adapter_client/migrations/0003_message_transaction_code_alter_config_journal_config_and_more.py
adapter_client/migrations/0004_alter_incomingmessage_id.py
adapter_client/migrations/0005_add_config_file_storage_config_file_storage_config.py
adapter_client/migrations/0006_alter_journalentry_options_alter_config_id_and_more.py
adapter_client/migrations/__init__.py
adapter_client-3.1.0.dist-info/METADATA
adapter_client-3.1.0.dist-info/WHEEL
adapter_client-3.1.0.dist-info/dependency_links.txt
adapter_client-3.1.0.dist-info/top_level.txt
adapter_client-3.1.0.dist-info/RECORD
