Metadata-Version: 2.4
Name: adapter-client
Version: 3.1.0
Summary: Клиент для взаимодействия со СМЭВ3 посредством Адаптера
Author: BARS Group
Author-email: education_dev@bars-open.ru
License: MIT
Classifier: Intended Audience :: Developers
Classifier: Environment :: Web Environment
Classifier: Natural Language :: Russian
Classifier: Operating System :: OS Independent
Classifier: Programming Language :: Python
Classifier: Programming Language :: Python :: 3.7
Classifier: Programming Language :: Python :: 3.8
Classifier: Programming Language :: Python :: 3.9
Classifier: Programming Language :: Python :: 3.10
Classifier: Programming Language :: Python :: 3.11
Classifier: Programming Language :: Python :: 3.12
Classifier: Development Status :: 5 - Production/Stable
Classifier: Framework :: Django :: 2.2
Classifier: Framework :: Django :: 3.0
Classifier: Framework :: Django :: 3.1
Classifier: Framework :: Django :: 3.2
Classifier: Framework :: Django :: 4.0
Classifier: Framework :: Django :: 4.1
Classifier: Framework :: Django :: 4.2
Classifier: Framework :: Django :: 5.0
Requires-Dist: pydantic<2.0,>=1.10.17
Requires-Dist: minio==6.0.2
Requires-Dist: zeep<4.2.0,>=4.1.0
Requires-Dist: django
Requires-Dist: celery<5.3.0; python_version == "3.7"
Requires-Dist: celery; python_version > "3.7"
Requires-Dist: django_celery_beat<2.6.0; python_version == "3.7"
Requires-Dist: django_celery_beat; python_version > "3.7"
Requires-Dist: django-postgres-partitioning==1.1.1
Provides-Extra: opensearch
Requires-Dist: opensearch-logger==1.2.2; extra == "opensearch"
Dynamic: author
Dynamic: author-email
Dynamic: classifier
Dynamic: description
Dynamic: description-content-type
Dynamic: license
Dynamic: provides-extra
Dynamic: requires-dist
Dynamic: summary
